{
  "scope": "ng911",
  "layer": "ProvisioningBoundary",
  "fieldInfos": [
    {
      "name": "DiscrpAgID",
      "category": "R",
      "domain": null
    },
    {
      "name": "DateUpdate",
      "category": "M",
      "domain": null
    },
    {
      "name": "Effective",
      "category": "O",
      "domain": null
    },
    {
      "name": "Expire",
      "category": "O",
      "domain": null
    },
    {
      "name": "PB_NGUID",
      "category": "M",
      "domain": null
    }
  ],
  "featureSet": {
    "geometryType": "esriGeometryPolygon",
    "spatialReference": {
      "wkid": 4326
    },
    "fields": [
      {
        "name": "DiscrpAgID",
        "alias": "Discrepancy Agency ID",
        "type": "esriFieldTypeString",
        "length": 75
      },
      {
        "name": "DateUpdate",
        "alias": "Date Updated",
        "type": "esriFieldTypeDate",
        "length": null
      },
      {
        "name": "Effective",
        "alias": "Effective Date",
        "type": "esriFieldTypeDate",
        "length": null
      },
      {
        "name": "Expire",
        "alias": "Expiration Date",
        "type": "esriFieldTypeDate",
        "length": null
      },
      {
        "name": "PB_NGUID",
        "alias": "Provisioning Boundary NENA Globally Unique ID",
        "type": "esriFieldTypeString",
        "length": 254
      }
    ],
    "features": []
  }
}